{
  "name": "Tax Strategy Comparison",
  "description": "Compare different tax optimization strategies for equity compensation",
  "scenarios": [
    "000_natural_evolution",
    "001_exercise_all_vested",
    "002_tender_and_donate"
  ],
  "price_scenario": "moderate",
  "projection_years": 5,
  "notes": [
    "This portfolio compares three core tax strategies:",
    "1. Natural Evolution - baseline do-nothing scenario",
    "2. Exercise All Vested - immediate exercise to start LTCG clock",
    "3. Tender and Donate - balanced liquidity and charity approach",
    "Additional strategies (AMT Optimization, Exercise at IPO) can be added as numbered scenarios."
  ]
}
